happymongo/__init__.py
happymongo_py3-0.1.3.dist-info/LICENSE
happymongo_py3-0.1.3.dist-info/METADATA
happymongo_py3-0.1.3.dist-info/WHEEL
happymongo_py3-0.1.3.dist-info/top_level.txt
happymongo_py3-0.1.3.dist-info/RECORD
