Metadata-Version: 2.1
Name: happymongo-py3
Version: 0.1.3
Summary: Python module for making it easy and consistent to connect to MongoDB via PyMongo either in Flask or in a non-flask application
Home-page: https://github.com/sivel/happymongo
Author: Matt Martz
Author-email: matt@sivel.net
License: Apache License, Version 2.0
Platform: UNKNOWN
Requires-Dist: pymongo
